Metadata-Version: 2.4
Name: dynamic_functioneer
Version: 1.1.1
Summary: A Python package for dynamic function and method handling with LLM support.
Home-page: https://github.com/eramireztorres/DynamicFunctioneer
Author: Erick Eduardo Ramirez Torres
Author-email: Erick Eduardo Ramirez Torres <erickeduardoramireztorres@gmail.com>
License: MIT
Keywords: dynamic,methods,functions,LLM,hot-swapping
Requires-Python: >=3.11
License-File: LICENSE
Requires-Dist: astunparse
Requires-Dist: uv
Requires-Dist: openai>=1.64.0
Requires-Dist: httpx>=0.28.1
Requires-Dist: requests>=2.32.3
Requires-Dist: google-genai>=1.3.0
Requires-Dist: anthropic>=0.49.0
Requires-Dist: crewai
Requires-Dist: litellm>=1.65.3
Provides-Extra: dev
Requires-Dist: pytest>=6.0; extra == "dev"
Requires-Dist: pytest-cov; extra == "dev"
Requires-Dist: black; extra == "dev"
Requires-Dist: flake8; extra == "dev"
Requires-Dist: mypy; extra == "dev"
Provides-Extra: docs
Requires-Dist: sphinx; extra == "docs"
Requires-Dist: sphinx-rtd-theme; extra == "docs"
Dynamic: author
Dynamic: home-page
Dynamic: license-file
Dynamic: requires-python
